skymap_eofactory_data/__init__.py
skymap_eofactory_data/data.py
skymap_eofactory_data/image.py
skymap_eofactory_data/table.py
skymap_eofactory_data/vector.py
skymap_eofactory_data-1.0.17.dist-info/LICENSE
skymap_eofactory_data-1.0.17.dist-info/METADATA
skymap_eofactory_data-1.0.17.dist-info/WHEEL
skymap_eofactory_data-1.0.17.dist-info/top_level.txt
skymap_eofactory_data-1.0.17.dist-info/RECORD
