Metadata-Version: 2.1
Name: skymap-eofactory-data
Version: 1.0.17
Summary: A storage data of eofactory
Author: Nguyen Van Trien
Author-email: trien.nv195934@gmail.com
Keywords: eofactory,skymap,data
Classifier: Programming Language :: Python :: 3
Classifier: License :: OSI Approved :: MIT License
Classifier: Operating System :: OS Independent
Classifier: Operating System :: Microsoft :: Windows
License-File: LICENSE
Requires-Dist: python-dotenv
